nadar/__init__.py
nadar/core.py
nadar/helper.py
nadar-0.1.0.dist-info/LICENSE.txt
nadar-0.1.0.dist-info/METADATA
nadar-0.1.0.dist-info/WHEEL
nadar-0.1.0.dist-info/top_level.txt
nadar-0.1.0.dist-info/RECORD
