Metadata-Version: 2.1
Name: nadar
Version: 0.1.0
Summary: NAtural DAte Ranges - automatic translation of natural language phrases describing date ranges into relevant dates or strings
Home-page: https://github.com/michalpuchala/nadar
Author: Michal Puchala
Author-email: mk.puchala@gmail.com
License: UNKNOWN
Platform: UNKNOWN
Classifier: Programming Language :: Python :: 3
Classifier: License :: OSI Approved :: MIT License
Classifier: Operating System :: OS Independent
Requires-Python: >=3.6
Requires-Dist: datetime
Requires-Dist: dateparser
